ddpaw/analysis.py
ddpaw/cli.py
ddpaw/datastructure.py
ddpaw/typed.py
ddpaw/utils.py
ddpaw-0.1.1.dist-info/LICENSE
ddpaw-0.1.1.dist-info/METADATA
ddpaw-0.1.1.dist-info/WHEEL
ddpaw-0.1.1.dist-info/entry_points.txt
ddpaw-0.1.1.dist-info/RECORD
