Metadata-Version: 2.1
Name: ddpaw
Version: 0.1.1
Summary: Extract APM metrics from DataDog
Author: benbenbang
Author-email: ben.chen@vestiairecollective.com
Requires-Python: >=3.10,<4.0
Classifier: Programming Language :: Python :: 3
Classifier: Programming Language :: Python :: 3.10
Classifier: Programming Language :: Python :: 3.11
Classifier: Programming Language :: Python :: 3.12
Provides-Extra: all
Provides-Extra: fast
Provides-Extra: plot
Requires-Dist: click (>=8.1,<8.2)
Requires-Dist: datadog-api-client (>=2.23,<2.24)
Requires-Dist: pydantic-settings (>=2.2,<2.3)
Requires-Dist: scipy (>=1.13,<1.14) ; extra == "all" or extra == "fast"
Requires-Dist: seaborn (>=0.13,<0.14) ; extra == "all" or extra == "plot"
